bm_cli/__init__.py
bm_cli/bmpy_utils.py
bm_cli/runtime_CLI.py
bm_cli/sswitch_CLI.py
bm_runtime/__init__.py
bm_runtime/simple_pre/SimplePre.py
bm_runtime/simple_pre/__init__.py
bm_runtime/simple_pre/constants.py
bm_runtime/simple_pre/ttypes.py
bm_runtime/simple_pre_lag/SimplePreLAG.py
bm_runtime/simple_pre_lag/__init__.py
bm_runtime/simple_pre_lag/constants.py
bm_runtime/simple_pre_lag/ttypes.py
bm_runtime/standard/Standard.py
bm_runtime/standard/__init__.py
bm_runtime/standard/constants.py
bm_runtime/standard/ttypes.py
p4_simple_switch_cli-1.0.0.data/scripts/simple_switch_CLI
sswitch_runtime/SimpleSwitch.py
sswitch_runtime/__init__.py
sswitch_runtime/constants.py
sswitch_runtime/ttypes.py
p4_simple_switch_cli-1.0.0.dist-info/METADATA
p4_simple_switch_cli-1.0.0.dist-info/WHEEL
p4_simple_switch_cli-1.0.0.dist-info/top_level.txt
p4_simple_switch_cli-1.0.0.dist-info/RECORD
