Metadata-Version: 2.1
Name: p4-simple-switch-cli
Version: 1.0.0
Summary: Stand-alone packaging of P4 behavioral-model client tool
Home-page: https://github.com/bluecmd/p4-tools
Author: Christian Svensson
Author-email: blue@cmd.nu
License: UNKNOWN
Project-URL: Bug Tracker, https://github.com/bluecmd/p4-tools/issues
Platform: UNKNOWN
Classifier: Programming Language :: Python :: 3
Classifier: License :: OSI Approved :: Apache Software License
Classifier: Operating System :: OS Independent
Requires-Python: >=3.6
Requires-Dist: thrift
